pyproject_toml/__init__.py
pyproject_toml/project.py
pyproject_toml/utils.py
pyproject_toml/build_system/__init__.py
pyproject_toml/build_system/build_backend.py
pyproject_toml-0.1.0.dist-info/METADATA
pyproject_toml-0.1.0.dist-info/WHEEL
pyproject_toml-0.1.0.dist-info/top_level.txt
pyproject_toml-0.1.0.dist-info/RECORD
